LICENSE
README.md
setup.py
calcupy/__init__.py
calcupy/calculator.py
calcupy/check_types.py
calcupy/commands.py
calcupy/evaluator.py
calcupy/settings.py
calcupy/variables.py
calcupy.egg-info/PKG-INFO
calcupy.egg-info/SOURCES.txt
calcupy.egg-info/dependency_links.txt
calcupy.egg-info/top_level.txt